glpi_python_sdk/__init__.py
glpi_python_sdk/connection.py
glpi_python_sdk/connection_legacy.py
glpi_python_sdk/exceptions.py
glpi_python_sdk/helpers.py
glpi_python_sdk/http_client.py
glpi_python_sdk/models.py
glpi_python_sdk/resources/__init__.py
glpi_python_sdk/resources/auth.py
glpi_python_sdk/resources/documents.py
glpi_python_sdk/resources/tickets.py
glpi_python_sdk-2.1.0.dist-info/METADATA
glpi_python_sdk-2.1.0.dist-info/WHEEL
glpi_python_sdk-2.1.0.dist-info/RECORD
