Metadata-Version: 2.4
Name: glpi-python-sdk
Version: 2.1.0
Summary: Modern Python SDK for GLPI REST API with sync/async support
Project-URL: Homepage, https://github.com/codebunker/glpi-python-sdk
Project-URL: Documentation, https://glpi-python-sdk.codebunker.net
Project-URL: Repository, https://github.com/codebunker/glpi-python-sdk
Project-URL: Issues, https://github.com/codebunker/glpi-python-sdk/issues
Author-email: Tarcisio Miranda <eu@tarcisio.me>
License-Expression: MIT
Keywords: api,assets,async,fastapi,glpi,helpdesk,itsm,sdk,tickets
Classifier: Development Status :: 4 - Beta
Classifier: Framework :: FastAPI
Classifier: Intended Audience :: Developers
Classifier: License :: OSI Approved :: MIT License
Classifier: Operating System :: OS Independent
Classifier: Programming Language :: Python :: 3
Classifier: Programming Language :: Python :: 3.10
Classifier: Programming Language :: Python :: 3.11
Classifier: Programming Language :: Python :: 3.12
Classifier: Programming Language :: Python :: 3.13
Classifier: Topic :: Software Development :: Libraries :: Python Modules
Classifier: Typing :: Typed
Requires-Python: >=3.10
Requires-Dist: arrow>=1.3.0
Requires-Dist: httpx>=0.25.0
Requires-Dist: leopards>=0.1.3
Requires-Dist: typing-extensions>=4.8.0
Provides-Extra: all
Requires-Dist: anyio>=4.0.0; extra == 'all'
Requires-Dist: build>=1.0.0; extra == 'all'
Requires-Dist: fastapi>=0.100.0; extra == 'all'
Requires-Dist: httpx[http2]>=0.25.0; extra == 'all'
Requires-Dist: mkdocs-material>=9.4.0; extra == 'all'
Requires-Dist: mkdocs>=1.5.0; extra == 'all'
Requires-Dist: mkdocstrings[python]>=0.23.0; extra == 'all'
Requires-Dist: mypy>=1.6.0; extra == 'all'
Requires-Dist: pre-commit>=3.5.0; extra == 'all'
Requires-Dist: pytest-asyncio>=0.21.0; extra == 'all'
Requires-Dist: pytest-cov>=4.1.0; extra == 'all'
Requires-Dist: pytest>=7.4.0; extra == 'all'
Requires-Dist: ruff>=0.1.0; extra == 'all'
Requires-Dist: twine>=4.0.0; extra == 'all'
Provides-Extra: anyio
Requires-Dist: anyio>=4.0.0; extra == 'anyio'
Provides-Extra: dev
Requires-Dist: build>=1.0.0; extra == 'dev'
Requires-Dist: mypy>=1.6.0; extra == 'dev'
Requires-Dist: pre-commit>=3.5.0; extra == 'dev'
Requires-Dist: pytest-asyncio>=0.21.0; extra == 'dev'
Requires-Dist: pytest-cov>=4.1.0; extra == 'dev'
Requires-Dist: pytest>=7.4.0; extra == 'dev'
Requires-Dist: ruff>=0.1.0; extra == 'dev'
Requires-Dist: twine>=4.0.0; extra == 'dev'
Provides-Extra: docs
Requires-Dist: mkdocs-material>=9.4.0; extra == 'docs'
Requires-Dist: mkdocs>=1.5.0; extra == 'docs'
Requires-Dist: mkdocstrings[python]>=0.23.0; extra == 'docs'
Provides-Extra: fastapi
Requires-Dist: anyio>=4.0.0; extra == 'fastapi'
Requires-Dist: fastapi>=0.100.0; extra == 'fastapi'
Provides-Extra: http2
Requires-Dist: httpx[http2]>=0.25.0; extra == 'http2'
